cymod/__init__.py
cymod/__main__.py
cymod/customise.py
cymod/cybase.py
cymod/cyproc.py
cymod/load.py
cymod/params.py
cymod/tabproc.py
cymod/transtable.py
cymod-0.0.5.dist-info/LICENSE
cymod-0.0.5.dist-info/METADATA
cymod-0.0.5.dist-info/WHEEL
cymod-0.0.5.dist-info/top_level.txt
cymod-0.0.5.dist-info/RECORD
