Metadata-Version: 2.1
Name: cymod
Version: 0.0.5
Summary: Process files containing Cypher queries describing complicated models.
Home-page: https://github.com/lanecodes/cymod
Author: Andrew Lane
Author-email: ajlane50@gmail.com
License: MIT
Platform: UNKNOWN
Classifier: License :: OSI Approved :: MIT License
Classifier: Development Status :: 2 - Pre-Alpha
Classifier: Programming Language :: Python
Classifier: Programming Language :: Python :: 2
Classifier: Programming Language :: Python :: 2.7
Classifier: Programming Language :: Python :: 3
Classifier: Programming Language :: Python :: 3.5
Classifier: Programming Language :: Python :: 3.6
Classifier: Programming Language :: Python :: 3.7
Classifier: Programming Language :: Python :: Implementation :: CPython
Classifier: Programming Language :: Python :: Implementation :: Jython
Requires-Python: >=2.7
Requires-Dist: neo4j-driver (>=1.6.0)
Requires-Dist: pandas
